mycalc/calculator.py
Jinseoung-0.0.1.dist-info/METADATA
Jinseoung-0.0.1.dist-info/WHEEL
Jinseoung-0.0.1.dist-info/top_level.txt
Jinseoung-0.0.1.dist-info/RECORD
