Metadata-Version: 2.1
Name: Jinseoung
Version: 0.0.1
Summary: nice calculator
Home-page: https://github.com/LSjin16/1st-oss
Author: sjchun
License: UNKNOWN
Platform: UNKNOWN
Classifier: Programming Language :: Python :: 3
